protein_mpnn/__init__.py
protein_mpnn/protein_mpnn_run.py
protein_mpnn/protein_mpnn_utils.py
protein_mpnn/helper_scripts/__init__.py
protein_mpnn/helper_scripts/assign_fixed_chains.py
protein_mpnn/helper_scripts/make_bias_AA.py
protein_mpnn/helper_scripts/make_bias_per_res_dict.py
protein_mpnn/helper_scripts/make_fixed_positions_dict.py
protein_mpnn/helper_scripts/make_pos_neg_tied_positions_dict.py
protein_mpnn/helper_scripts/make_pssm_input_dict.py
protein_mpnn/helper_scripts/make_tied_positions_dict.py
protein_mpnn/helper_scripts/parse_multiple_chains.py
protein_mpnn/helper_scripts/other_tools/make_omit_AA.py
protein_mpnn/helper_scripts/other_tools/make_pssm_dict.py
protein_mpnn/training/model_utils.py
protein_mpnn/training/training.py
protein_mpnn/training/utils.py
protein_mpnn_pip-0.0.1.dist-info/LICENSE
protein_mpnn_pip-0.0.1.dist-info/METADATA
protein_mpnn_pip-0.0.1.dist-info/WHEEL
protein_mpnn_pip-0.0.1.dist-info/top_level.txt
protein_mpnn_pip-0.0.1.dist-info/RECORD
