Metadata-Version: 2.1
Name: protein-mpnn-pip
Version: 0.0.1
Summary: pip installable proteinmpnn 
Author-email: Theodore Sternlieb <tsternlieb@wesleyan.edu>
Project-URL: Homepage, https://github.com/tsteternlieb/ProteinMPNN
Project-URL: Bug Tracker, https://github.com/tsteternlieb/ProteinMPNN/issues
Classifier: Programming Language :: Python :: 3
Classifier: License :: OSI Approved :: MIT License
Classifier: Operating System :: OS Independent
Requires-Python: >=3.8
License-File: LICENSE
